scrapy_nc/db/__init__.py
scrapy_nc/db/mongo.py
scrapy_nc/helper/__init__.py
scrapy_nc/helper/tools.py
scrapy_nc/item/__init__.py
scrapy_nc/item/base_item.py
scrapy_nc/item/news_item.py
scrapy_nc/log_formatter/__init__.py
scrapy_nc/middlewares/__init__.py
scrapy_nc/middlewares/proxy_downloader_middleware.py
scrapy_nc/pipelines/__init__.py
scrapy_nc/pipelines/amqp_pipeline.py
scrapy_nc/pipelines/flow_pipeline.py
scrapy_nc/pipelines/mongo_pipeline.py
scrapy_nc/pipelines/preprocess_pipeline.py
scrapy_nc/queue/__init__.py
scrapy_nc/queue/producer.py
scrapy_nc/spiders/__init__.py
scrapy_nc/spiders/notifier.py
scrapy_nc-0.2.21.dist-info/LICENSE
scrapy_nc-0.2.21.dist-info/METADATA
scrapy_nc-0.2.21.dist-info/WHEEL
scrapy_nc-0.2.21.dist-info/top_level.txt
scrapy_nc-0.2.21.dist-info/RECORD
