Metadata-Version: 2.1
Name: scrapy-nc
Version: 0.2.21
Summary: Scrapy plugins in NoCode
Home-page: https://github.com/fantasy/scrapy_nc
Author: fantasy614@nocode.com
Classifier: Framework :: Scrapy
Classifier: Development Status :: 5 - Production/Stable
Classifier: Environment :: Console
Classifier: Intended Audience :: Developers
Classifier: Operating System :: OS Independent
Classifier: Programming Language :: Python
Classifier: Programming Language :: Python :: 3
Classifier: Programming Language :: Python :: 3.4
Classifier: Programming Language :: Python :: 3.5
Classifier: Programming Language :: Python :: 3.6
Classifier: Programming Language :: Python :: 3.7
Classifier: Programming Language :: Python :: 3.8
Classifier: Programming Language :: Python :: 3.9
Classifier: Topic :: Utilities
Classifier: Framework :: Scrapy
Requires: scrapy (>=0.24.5)
License-File: LICENSE
Requires-Dist: scrapy
Requires-Dist: requests
